thonnycontrib/onedark/__init__.py
thonny_onedark-0.2.0.dist-info/LICENSE
thonny_onedark-0.2.0.dist-info/METADATA
thonny_onedark-0.2.0.dist-info/WHEEL
thonny_onedark-0.2.0.dist-info/top_level.txt
thonny_onedark-0.2.0.dist-info/RECORD
