Metadata-Version: 2.1
Name: thonny-onedark
Version: 0.2.0
Summary: One Dark theme for Thonny IDE
Home-page: https://github.com/ranelpadon/thonny-onedark
Author: Ranel Padon
Author-email: ranel.padon@gmail.com
License: MIT
Download-URL: https://github.com/ranelpadon/thonny-onedark
Keywords: IDE education programming Thonny dark theme one-dark "one dark"
Platform: Windows
Platform: macOS
Platform: Linux
Classifier: Intended Audience :: Developers
Classifier: Intended Audience :: Education
Classifier: Intended Audience :: End Users/Desktop
Classifier: License :: OSI Approved :: MIT License
Classifier: Operating System :: MacOS
Classifier: Operating System :: Microsoft :: Windows
Classifier: Operating System :: POSIX
Classifier: Operating System :: POSIX :: Linux
Classifier: Programming Language :: Python
Classifier: Programming Language :: Python :: 3
Classifier: Topic :: Education
Classifier: Topic :: Software Development
Classifier: Topic :: Software Development :: Embedded Systems
License-File: LICENSE
Requires-Dist: thonny (>=3.0.0)
